LICENSE
bin/__init__.py
bin/bin.py
bin/bin_file/__init__.py
bin/bin_file/bin_file_loader.py
bin/bin_file/bin_file_resolver.py
bin/bin_file/dtos/__init__.py
bin/bin_file/dtos/base_bin_file_dto.py
bin/bin_file/dtos/bin_file_dto.py
bin/bin_file/dtos/bin_file_mapper.py
bin/bin_file/errors.py
bin/bin_file/init_command.py
bin/commands/__init__.py
bin/commands/command.py
bin/commands/command_help.py
bin/commands/errors.py
bin/commands/internal/__init__.py
bin/commands/internal/apply_env_command.py
bin/commands/internal/factory.py
bin/commands/internal/help_only_command.py
bin/commands/internal/log_title_command.py
bin/commands/internal/mute_logs_command.py
bin/commands/internal/noop_command.py
bin/commands/internal/unmute_logs_command.py
bin/commands/internal/with_setup_command.py
bin/custom_commands/__init__.py
bin/custom_commands/basic_command.py
bin/custom_commands/command_tree.py
bin/custom_commands/dtos/__init__.py
bin/custom_commands/dtos/base_custom_command_dto.py
bin/custom_commands/dtos/command_tree_dto.py
bin/custom_commands/dtos/custom_commands_mapper.py
bin/custom_commands/dtos/str_custom_command_dto.py
bin/env/__init__.py
bin/env/ejson_env_provider.py
bin/env/env.py
bin/env/env_provider.py
bin/env/env_providers.py
bin/env/errors.py
bin/env/log_env_command.py
bin/error_handler.py
bin/main.py
bin/models/__init__.py
bin/models/bin_base_model.py
bin/models/sem_ver_spec.py
bin/models/str_command.py
bin/process/__init__.py
bin/process/emoji.py
bin/process/helpable.py
bin/process/io/__init__.py
bin/process/io/console_io.py
bin/process/io/io.py
bin/process/io/mute_io.py
bin/process/process.py
bin/process/process_result.py
bin/requirements/__init__.py
bin/requirements/dtos/__init__.py
bin/requirements/dtos/base_requirement_dto.py
bin/requirements/dtos/python_requirement_dto.py
bin/requirements/dtos/requirements_command_mapper.py
bin/requirements/dtos/sem_ver_requirement_dto.py
bin/requirements/dtos/shell_requirement_dto.py
bin/requirements/requirement.py
sbin-1.1.1.dist-info/LICENSE
sbin-1.1.1.dist-info/METADATA
sbin-1.1.1.dist-info/WHEEL
sbin-1.1.1.dist-info/entry_points.txt
sbin-1.1.1.dist-info/RECORD
